peewee_tidb.py
peewee_tidb-0.1.1.dist-info/LICENSE
peewee_tidb-0.1.1.dist-info/METADATA
peewee_tidb-0.1.1.dist-info/WHEEL
peewee_tidb-0.1.1.dist-info/top_level.txt
peewee_tidb-0.1.1.dist-info/RECORD
