Metadata-Version: 2.1
Name: peewee-tidb
Version: 0.1.1
Summary: A peewee extension for TiDB.
Author-email: wd0517 <me@wangdi.ink>
License: MIT License
Project-URL: Homepage, https://github.com/wd0517/peewee-tidb
Project-URL: Bug Reports, https://github.com/wd0517/peewee-tidb/issues
Project-URL: Source, https://github.com/wd0517/peewee-tidb
Keywords: peewee,tidb
Classifier: Development Status :: 5 - Production/Stable
Classifier: Intended Audience :: Developers
Classifier: License :: OSI Approved :: MIT License
Classifier: Operating System :: OS Independent
Classifier: Programming Language :: Python
Classifier: Programming Language :: Python :: 3
Classifier: Programming Language :: Python :: 3.7
Classifier: Programming Language :: Python :: 3.8
Classifier: Programming Language :: Python :: 3.9
Classifier: Programming Language :: Python :: 3.10
Classifier: Programming Language :: Python :: 3.11
Classifier: Programming Language :: Python :: 3.12
Requires-Python: >=3.7
License-File: LICENSE
Requires-Dist: peewee
